thumb_gen/__init__.py
thumb_gen/__main__.py
thumb_gen/application.py
thumb_gen/config.py
thumb_gen/utils.py
thumb_gen/version.py
thumb_gen/viewer.py
thumb_gen/worker.py
thumb_gen/fonts/RobotoCondensed-Regular.ttf
thumb_gen-4.0.1.dist-info/LICENSE
thumb_gen-4.0.1.dist-info/METADATA
thumb_gen-4.0.1.dist-info/WHEEL
thumb_gen-4.0.1.dist-info/entry_points.txt
thumb_gen-4.0.1.dist-info/top_level.txt
thumb_gen-4.0.1.dist-info/RECORD
