Metadata-Version: 2.1
Name: thumb-gen
Version: 4.0.1
Summary: Python application that can be used to generate video thumbnail for mp4 and mkv file types.
Home-page: https://github.com/truethari/thumb-gen
Author: tharindu.dev
Author-email: tharindu.nm@yahoo.com
License: MIT
Project-URL: Bug Tracker, https://github.com/truethari/thumb-gen/issues
Keywords: thumbnails video screenshot
Platform: UNKNOWN
Classifier: Programming Language :: Python :: 3
Classifier: License :: OSI Approved :: MIT License
License-File: LICENSE
Requires-Dist: Pillow
Requires-Dist: infomedia
Requires-Dist: opencv-python
